[
  {
    "open": 28570.31,
    "high": 28595.75,
    "low": 28465.36,
    "close": 28465.36,
    "volume": 1377.36769,
    "timestamp": 1680307199999
  },
  {
    "open": 28465.36,
    "high": 28547.2,
    "low": 28408.57,
    "close": 28438.27,
    "volume": 1524.81719,
    "timestamp": 1680310799999
  },
  {
    "open": 28438.26,
    "high": 28625.61,
    "low": 28410.35,
    "close": 28610.63,
    "volume": 1458.59279,
    "timestamp": 1680314399999
  },
  {
    "open": 28610.62,
    "high": 28819.71,
    "low": 28467.31,
    "close": 28583.36,
    "volume": 3522.34366,
    "timestamp": 1680317999999
  },
  {
    "open": 28583.36,
    "high": 28603.78,
    "low": 28503.29,
    "close": 28541.1,
    "volume": 1088.35997,
    "timestamp": 1680321599999
  }
]
